realms/__init__.py
realms/display.py
realms/game.py
realms-0.1.0.dist-info/METADATA
realms-0.1.0.dist-info/WHEEL
realms-0.1.0.dist-info/RECORD
