Metadata-Version: 2.1
Name: realms
Version: 0.1.0
Summary: An simple, powerful Python game engine
License: GPL-3.0-or-later
Author: Dylan Rogers
Author-email: opendylan@proton.me
Requires-Python: >=3,<4
Classifier: License :: OSI Approved :: GNU General Public License v3 or later (GPLv3+)
Classifier: Programming Language :: Python :: 3
Classifier: Programming Language :: Python :: 3.4
Classifier: Programming Language :: Python :: 3.5
Classifier: Programming Language :: Python :: 3.6
Classifier: Programming Language :: Python :: 3.7
Classifier: Programming Language :: Python :: 3.8
Classifier: Programming Language :: Python :: 3.9
Classifier: Programming Language :: Python :: 3.10
Classifier: Programming Language :: Python :: 3.11
Requires-Dist: pygame (>=2,<3)
